{
  "created_at": "2025-08-28T11:00:35.521761+00:00",
  "elapsed": 1.222248,
  "encoding": "utf-8",
  "headers": {
    "Access-Control-Allow-Headers": "*",
    "Access-Control-Allow-Origin": "*",
    "Cache-Control": "public, max-age=300, must-revalidate",
    "Connection": "keep-alive",
    "Content-Encoding": "gzip",
    "Content-Security-Policy": "object-src 'none'; script-src 'unsafe-inline' 'unsafe-eval' 'strict-dynamic' https: http:;",
    "Content-Type": "application/json;charset=utf-8",
    "Date": "Thu, 28 Aug 2025 11:00:35 GMT",
    "ETag": "W/\"20AA_250804F;1753892432;3.1.335\"",
    "Strict-Transport-Security": "max-age=31536000; includeSubDomains; preload",
    "Transfer-Encoding": "chunked",
    "Vary": "Accept",
    "X-Cache-Status": "MISS",
    "X-Content-Type-Options": "nosniff",
    "X-Download-Options": "noopen",
    "X-Frame-Options": "DENY",
    "X-Permitted-Cross-Domain-Policies": "none",
    "X-XSS-Protection": "1; mode=block"
  },
  "reason": "OK",
  "request": {
    "body": "",
    "headers": {
      "Accept": "*/*",
      "Accept-Encoding": "gzip, deflate",
      "Connection": "keep-alive",
      "User-Agent": "python-requests/2.32.5"
    },
    "method": "GET",
    "url": "https://rxnav.nlm.nih.gov/REST/rxcui/9230/historystatus.json"
  },
  "status_code": 200,
  "url": "https://rxnav.nlm.nih.gov/REST/rxcui/9230/historystatus.json",
  "_decoded_content": {
    "rxcuiStatusHistory": {
      "metaData": {
        "status": "Active",
        "source": "RXNORM",
        "releaseStartDate": "042005",
        "releaseEndDate": "",
        "isCurrent": "YES",
        "activeStartDate": "042005",
        "activeEndDate": "",
        "remappedDate": ""
      },
      "attributes": {
        "rxcui": "9230",
        "name": "Reglan",
        "tty": "BN",
        "isMultipleIngredient": "NO",
        "isBranded": "YES"
      },
      "definitionalFeatures": {},
      "pack": {},
      "derivedConcepts": {
        "ingredientConcept": [
          {
            "ingredientRxcui": "6915",
            "ingredientName": "metoclopramide"
          }
        ]
      }
    }
  }
}